selenium_swift/__init__.py
selenium_swift/alert_handler.py
selenium_swift/browser.py
selenium_swift/element.py
selenium_swift/extensions.py
selenium_swift/json_handler.py
selenium_swift/mouse_controller.py
selenium_swift/page_event.py
selenium_swift/web_downloader.py
selenium_swift/web_option.py
selenium_swift/web_service.py
selenium_swift/captcha_to_solve/_2captcha.py
selenium_swift/captcha_to_solve/__init__.py
selenium_swift/captcha_to_solve/ai_captcha.py
selenium_swift-0.1.6.dist-info/LICENSE
selenium_swift-0.1.6.dist-info/METADATA
selenium_swift-0.1.6.dist-info/WHEEL
selenium_swift-0.1.6.dist-info/top_level.txt
selenium_swift-0.1.6.dist-info/RECORD
