Metadata-Version: 2.1
Name: selenium_swift
Version: 0.1.6
Summary: A high-performance async web scraping and automation framework using Selenium.
Home-page: https://github.com/Mo7amed-logic/selenium_swift
Author: Mo7amed-logic
Author-email: medhasnaoui833@gmail.com
Project-URL: Bug Reports, https://github.com/Mo7amed-logic/selenium_swift/issues
Project-URL: Source, https://github.com/Mo7amed-logic/selenium_swift
Classifier: Programming Language :: Python :: 3
Classifier: Programming Language :: Python :: 3.8
Classifier: Programming Language :: Python :: 3.9
Classifier: Operating System :: OS Independent
Classifier: Intended Audience :: Developers
Classifier: Topic :: Internet :: WWW/HTTP
Classifier: Topic :: Internet :: WWW/HTTP :: Dynamic Content
Classifier: Topic :: Software Development :: Libraries :: Python Modules
Requires-Python: >=3.6
License-File: LICENSE
Requires-Dist: setuptools
Requires-Dist: selenium>=4.0.0
Requires-Dist: aiohttp>=3.7.4
Requires-Dist: webdriver-manager>=3.5.0
Requires-Dist: undetected-chromedriver>=3.0.0
Requires-Dist: requests>=2.25.1
Requires-Dist: Pillow>=8.0.0
